MANIFEST.in
README.md
requirements.txt
setup.cfg
setup.py
test-requirements.txt
cocoon/__init__.py
cocoon/cui.py
cocoon/task.py
cocoon_framework.egg-info/PKG-INFO
cocoon_framework.egg-info/SOURCES.txt
cocoon_framework.egg-info/dependency_links.txt
cocoon_framework.egg-info/entry_points.txt
cocoon_framework.egg-info/pbr.json
cocoon_framework.egg-info/requires.txt
cocoon_framework.egg-info/top_level.txt