Metadata-Version: 1.1
Name: cocoon-framework
Version: 0.1.1
Summary: Workflow Management Framework
Home-page: https://github.com/treasure-data/cocoon
Author: Taro L. Saito
Author-email: leo@xerial.org
License: Apache License, Version 2.0
Keywords: workflow SQL dataflow
Platform: UNKNOWN
Classifier: Development Status :: 3 - Alpha
Classifier: Intended Audience :: Science/Research
Classifier: Topic :: Scientific/Engineering
Classifier: License :: OSI Approved :: Apache Software License
Classifier: Programming Language :: Python :: 2
Classifier: Programming Language :: Python :: 2.6
Classifier: Programming Language :: Python :: 2.7
Classifier: Programming Language :: Python :: 3
Classifier: Programming Language :: Python :: 3.2
Classifier: Programming Language :: Python :: 3.3
Classifier: Programming Language :: Python :: 3.4
